LICENSE
MANIFEST.in
Makefile
README
jslint-cli
setup.py
jslint/__init__.py
jslint/fulljslint.js
jslint/json2.js
jslint/lintwrapper.js
jslint/spidermonkey.py
jslint/util.py
jslint.egg-info/PKG-INFO
jslint.egg-info/SOURCES.txt
jslint.egg-info/dependency_links.txt
jslint.egg-info/not-zip-safe
jslint.egg-info/top_level.txt
test/__init__.py