Metadata-Version: 1.0
Name: jslint
Version: 0.6.0
Summary: command-line wrapper for JSLint
Home-page: http://pypi.python.org/pypi/jslint
Author: FND
Author-email: FNDo@gmx.net
License: BSD
Platform: Posix; MacOS X; Windows
